aio_task_bound_context/__init__.py
aio_task_bound_context-0.1.0.dist-info/METADATA
aio_task_bound_context-0.1.0.dist-info/RECORD
aio_task_bound_context-0.1.0.dist-info/WHEEL
aio_task_bound_context-0.1.0.dist-info/top_level.txt
