Metadata-Version: 2.1
Name: aio-task-bound-context
Version: 0.1.0
Summary: Context manager that provides a means for context to be set, and retrieved in Python AsyncIO.
Home-page: https://github.com/rickycook/aio_task_bound_context/
Author: Ricky Cook
Author-email: pypi@auto.thatpanda.com
License: UNKNOWN
Platform: UNKNOWN
Classifier: Programming Language :: Python :: 3
Classifier: License :: OSI Approved :: MIT License
Classifier: Operating System :: OS Independent
